{
  "highScores": [
    {
      "name": "Madison ",
      "score": 371,
      "dateTime": "1/27/2023, 10:33:58 AM",
      "id": 1
    },
    {
      "name": "Forrest",
      "score": 110,
      "dateTime": "1/27/2023, 10:34:08 AM",
      "id": 2
    },
    {
      "name": "Jevin",
      "score": 708,
      "dateTime": "1/27/2023, 10:34:20 AM",
      "id": 3
    },
    {
      "name": "Jevin",
      "score": 96,
      "dateTime": "1/27/2023, 10:34:33 AM",
      "id": 4
    },
    {
      "name": "Madison",
      "score": 297,
      "dateTime": "1/27/2023, 10:34:48 AM",
      "id": 5
    },
    {
      "name": "Madison",
      "score": 781,
      "dateTime": "1/27/2023, 10:35:14 AM",
      "id": 6
    }
  ]
}